optilibre/__init__.py
optilibre/__main__.py
optilibre/_version.py
optilibre/cli.py
optilibre/core.py
optilibre/enums.py
optilibre/helpers.py
optilibre/models.py
optilibre/runner.py
optilibre/utils/__init__.py
optilibre/utils/parsers.py
optilibre-2.0.0.dist-info/LICENSE
optilibre-2.0.0.dist-info/METADATA
optilibre-2.0.0.dist-info/WHEEL
optilibre-2.0.0.dist-info/entry_points.txt
optilibre-2.0.0.dist-info/top_level.txt
optilibre-2.0.0.dist-info/RECORD
