Metadata-Version: 2.1
Name: optilibre
Version: 2.0.0
Summary: Video and Image optimizer
Author: Sydney Gems, <sydney@gems.technology>
Project-URL: Homepage, https://gitlab.com/daufinsyd/optilibre
Project-URL: Issues, https://gitlab.com/daufinsyd/optilibre/-/issues
Classifier: Programming Language :: Python :: 3
Classifier: License :: OSI Approved :: GNU Affero General Public License v3 or later (AGPLv3+)
Classifier: Operating System :: POSIX :: Linux
Requires-Python: >=3.8
License-File: LICENSE
Requires-Dist: coloredlogs
Requires-Dist: filetype
Requires-Dist: toml
Requires-Dist: click
